rag_agent/__init__.py
rag_agent/basic_auth.py
rag_agent/config.py
rag_agent/dataset_router.py
rag_agent/main.py
rag_agent/rag_agent_client.py
rag_agent/server.py
rag_agent/supabase_auth.py
rag_agent/client/__init__.py
rag_agent/client/light_rag_server_api_client/__init__.py
rag_agent/client/light_rag_server_api_client/client.py
rag_agent/client/light_rag_server_api_client/errors.py
rag_agent/client/light_rag_server_api_client/py.typed
rag_agent/client/light_rag_server_api_client/types.py
rag_agent/client/light_rag_server_api_client/api/__init__.py
rag_agent/client/light_rag_server_api_client/api/default/__init__.py
rag_agent/client/light_rag_server_api_client/api/default/get_auth_status_auth_status_get.py
rag_agent/client/light_rag_server_api_client/api/default/get_status_health_get.py
rag_agent/client/light_rag_server_api_client/api/default/login_login_post.py
rag_agent/client/light_rag_server_api_client/api/default/redirect_to_webui_get.py
rag_agent/client/light_rag_server_api_client/api/documents/__init__.py
rag_agent/client/light_rag_server_api_client/api/documents/clear_documents_documents_delete.py
rag_agent/client/light_rag_server_api_client/api/documents/documents_documents_get.py
rag_agent/client/light_rag_server_api_client/api/documents/get_pipeline_status_documents_pipeline_status_get.py
rag_agent/client/light_rag_server_api_client/api/documents/insert_batch_documents_file_batch_post.py
rag_agent/client/light_rag_server_api_client/api/documents/insert_file_documents_file_post.py
rag_agent/client/light_rag_server_api_client/api/documents/insert_text_documents_text_post.py
rag_agent/client/light_rag_server_api_client/api/documents/insert_texts_documents_texts_post.py
rag_agent/client/light_rag_server_api_client/api/documents/scan_for_new_documents_documents_scan_post.py
rag_agent/client/light_rag_server_api_client/api/documents/upload_to_input_dir_documents_upload_post.py
rag_agent/client/light_rag_server_api_client/api/graph/__init__.py
rag_agent_mcp-0.1.5.dist-info/METADATA
rag_agent_mcp-0.1.5.dist-info/WHEEL
rag_agent_mcp-0.1.5.dist-info/entry_points.txt
rag_agent_mcp-0.1.5.dist-info/RECORD
