Metadata-Version: 2.4
Name: rag-agent-mcp
Version: 0.1.5
Summary: RAG Agent - MCP Server for LightRAG
Author-email: shemhamforash <killsterak16@gmail.com>
Requires-Python: >=3.11
Requires-Dist: attrs>=25.3.0
Requires-Dist: httpx>=0.28.1
Requires-Dist: mcp>=1.2.0
Requires-Dist: pydantic>=2.11
Requires-Dist: python-dotenv>=1.0.1
Provides-Extra: dev
Requires-Dist: mypy>=1.5.0; extra == 'dev'
Requires-Dist: ruff>=0.11.4; extra == 'dev'
